spark_datax_schema_tools/__init__.py
spark_datax_schema_tools/functions/__init__.py
spark_datax_schema_tools/functions/generator.py
spark_datax_schema_tools/utils/__init__.py
spark_datax_schema_tools/utils/config.py
spark_datax_schema_tools/utils/dataframe.py
spark_datax_schema_tools/utils/dictionary.py
spark_datax_schema_tools/utils/logger.py
spark_datax_schema_tools/utils/memory.py
spark_datax_schema_tools/utils/sofia.py
spark_datax_schema_tools/utils/time_execution.py
spark_datax_schema_tools/utils/utils.py
spark_datax_schema_tools/utils/files/datum/Fields.csv
spark_datax_schema_tools/utils/files/datum/Objects.csv
spark_datax_schema_tools/utils/files/sofia/DDNG-DS.xls
spark_datax_schema_tools/utils/files/sofia/DDNG-F.xls
spark_datax_schema_tools/utils/files/sofia/DDNG-O.xls
spark_datax_schema_tools/utils/templates/__init__.py
spark_datax_schema_tools/utils/templates/table.html
spark_datax_schema_tools-0.0.43.dist-info/LICENSE
spark_datax_schema_tools-0.0.43.dist-info/METADATA
spark_datax_schema_tools-0.0.43.dist-info/WHEEL
spark_datax_schema_tools-0.0.43.dist-info/top_level.txt
spark_datax_schema_tools-0.0.43.dist-info/RECORD
