Metadata-Version: 2.1
Name: spark-datax-schema-tools
Version: 0.0.43
Summary: spark_datax_schema_tools
Home-page: https://github.com/jonaqp/spark_datax_schema_tools/
Download-URL: https://github.com/jonaqp/spark_datax_schema_tools/archive/main.zip
Author: Jonathan Quiza
Author-email: jony327@gmail.com
Keywords: spark,datax,schema
Classifier: Development Status :: 5 - Production/Stable
Classifier: Intended Audience :: Developers
Classifier: Intended Audience :: Science/Research
Classifier: Topic :: Scientific/Engineering :: Artificial Intelligence
Classifier: License :: OSI Approved :: Apache Software License
Classifier: Programming Language :: Python :: 3.8
Classifier: Programming Language :: Python :: 3.7
License-File: LICENSE
Requires-Dist: certifi (==2022.9.24)
Requires-Dist: color-tools (==0.0.2)
Requires-Dist: cramjam (==2.6.2)
Requires-Dist: et-xmlfile (==1.1.0)
Requires-Dist: Faker (==10.0.0)
Requires-Dist: fastavro (==1.7.0)
Requires-Dist: fastparquet (==2022.11.0)
Requires-Dist: findspark (==2.0.1)
Requires-Dist: fsspec (==2022.11.0)
Requires-Dist: humanize (==4.4.0)
Requires-Dist: Jinja2 (==3.1.2)
Requires-Dist: MarkupSafe (==2.1.1)
Requires-Dist: numpy (==1.24.0rc1)
Requires-Dist: openpyxl (==3.0.9)
Requires-Dist: packaging (==21.3)
Requires-Dist: pandas (==1.5.2)
Requires-Dist: prettytable (==2.5.0)
Requires-Dist: py4j (==0.10.7)
Requires-Dist: pyarrow (==10.0.1)
Requires-Dist: pyparsing (==3.0.9)
Requires-Dist: pyspark (==2.4.3)
Requires-Dist: python-dateutil (==2.8.2)
Requires-Dist: pytz (==2022.6)
Requires-Dist: PyYAML (==6.0)
Requires-Dist: six (==1.16.0)
Requires-Dist: sizebytes-tools (==0.0.3)
Requires-Dist: text-unidecode (==1.3)
Requires-Dist: wcwidth (==0.2.5)
Requires-Dist: xlrd (==2.0.1)
